use_context/__init__.py
use_context-0.0.3.dist-info/LICENSE
use_context-0.0.3.dist-info/METADATA
use_context-0.0.3.dist-info/WHEEL
use_context-0.0.3.dist-info/top_level.txt
use_context-0.0.3.dist-info/RECORD
