Metadata-Version: 2.1
Name: use-context
Version: 0.0.3
Summary: UNKNOWN
Home-page: https://github.com/Cologler/use-context-python
Author: Cologler
Author-email: skyoflw@gmail.com
License: MIT License
Platform: UNKNOWN
Classifier: License :: OSI Approved :: MIT License
Classifier: Programming Language :: Python :: 3.7
